libname/__init__.py
libname/app.py
siddhesh-0.0.4.dist-info/METADATA
siddhesh-0.0.4.dist-info/WHEEL
siddhesh-0.0.4.dist-info/top_level.txt
siddhesh-0.0.4.dist-info/RECORD
