Metadata-Version: 2.1
Name: siddhesh
Version: 0.0.4
Summary: Check out Siddhesh Kulthe's profile, or send him a direct message!
Author: Siddhesh Kulthe
Author-email: <siddheshkulthe43@gmail.com>
Keywords: python,sid,siddhesh kulthe,profile,message,social,iamsid47
Classifier: Development Status :: 4 - Beta
Classifier: Intended Audience :: Developers
Classifier: Programming Language :: Python :: 3
Classifier: Operating System :: Unix
Classifier: Operating System :: MacOS :: MacOS X
Classifier: Operating System :: Microsoft :: Windows
Requires-Dist: requests
